SpeckCollect-0.1.1.data/scripts/main.py
speckcollect/__init__.py
speckcollect/cosine.py
speckcollect/create_images.py
speckcollect/dvs_collector.py
SpeckCollect-0.1.1.dist-info/LICENSE
SpeckCollect-0.1.1.dist-info/METADATA
SpeckCollect-0.1.1.dist-info/WHEEL
SpeckCollect-0.1.1.dist-info/top_level.txt
SpeckCollect-0.1.1.dist-info/RECORD
