Metadata-Version: 2.1
Name: SpeckCollect
Version: 0.1.1
Summary: SpeckCollect gathers events from a SynSense Speck2fDevKit and generates temporal representations of event streams
Home-page: https://github.com/AdamDHines/SpeckCollect
Author: Adam D Hines
Author-email: adam.hines@qut.edu.au
License: MIT
Keywords: neuromorphic computing,dynamic vision sensor
Classifier: Development Status :: 4 - Beta
Classifier: Intended Audience :: Developers
Classifier: License :: OSI Approved :: MIT License
Classifier: Programming Language :: Python :: 3.6
Classifier: Programming Language :: Python :: 3.7
Classifier: Programming Language :: Python :: 3.8
Classifier: Programming Language :: Python :: 3.9
Classifier: Programming Language :: Python :: 3.10
Classifier: Programming Language :: Python :: 3.11
Requires-Python: >=3.6, !=3.12.*
License-File: LICENSE
Requires-Dist: sinabs
Requires-Dist: samna
Requires-Dist: numpy
Requires-Dist: tqdm
Requires-Dist: matplotlib
